csskit/__init__.py
csskit/auxiliaries.py
csskit/blocks.py
csskit/common.py
csskit/grammars/__init__.py
csskit/grammars/data_model.py
csskit/grammars/definitions.py
csskit/grammars/utilities.py
csskit/grammars/generated/__init__.py
csskit-1.0.0.dist-info/AUTHORS.txt
csskit-1.0.0.dist-info/LICENSE.txt
csskit-1.0.0.dist-info/METADATA
csskit-1.0.0.dist-info/WHEEL
csskit-1.0.0.dist-info/top_level.txt
csskit-1.0.0.dist-info/RECORD
